mock_library/__init__.py
mock_library/check_env.py
mock_library/click_cmd.py
mock_library/functions.py
mock_library/library_test.py
mock_library_copy/__init__.py
mock_library_copy/functions.py
mock_library_copy/library_test.py
upload_to_pip_demo_v-0.0.4.dist-info/LICENSE
upload_to_pip_demo_v-0.0.4.dist-info/METADATA
upload_to_pip_demo_v-0.0.4.dist-info/WHEEL
upload_to_pip_demo_v-0.0.4.dist-info/entry_points.txt
upload_to_pip_demo_v-0.0.4.dist-info/top_level.txt
upload_to_pip_demo_v-0.0.4.dist-info/RECORD
